Metadata-Version: 2.1
Name: test-ai-appium
Version: 0.1.20
Summary: A package to bring ai to appium scripts.
Home-page: https://github.com/test-dot-ai/testai-python
Author: Chris Navrides
Author-email: chris@test.ai
License: UNKNOWN
Project-URL: Bug Tracker, https://github.com/test-dot-ai/testai-python/issues
Platform: UNKNOWN
Classifier: Programming Language :: Python :: 3
Classifier: License :: OSI Approved :: Apache Software License
Classifier: Operating System :: OS Independent
Requires-Python: >=3.6
License-File: LICENSE
Requires-Dist: appium-python-client
Requires-Dist: requests
